async_call-0.1.2.dist-info/METADATA
async_call-0.1.2.dist-info/RECORD
async_call-0.1.2.dist-info/WHEEL
async_call-0.1.2.dist-info/top_level.txt
call/__init__.py
