Metadata-Version: 2.1
Name: async-call
Version: 0.1.2
Summary: Thread-based, JS-like asynchronous calls for Python.
Home-page: https://gitlab.com/solarliner/call
Author: Nathan Graule
Author-email: solarliner@gmail.com
License: MIT
Platform: UNKNOWN
Classifier: Development Status :: 3 - Alpha
Classifier: License :: OSI Approved :: MIT License
Classifier: Programming Language :: Python
Classifier: Programming Language :: Python :: 2.7
Classifier: Programming Language :: Python :: 3.5
Classifier: Programming Language :: Python :: Implementation :: CPython
Classifier: Topic :: Software Development :: Libraries :: Python Modules
Requires-Dist: typing
